yaci_client/__init__.py
yaci_client/api/__init__.py
yaci_client/api/account_api/__init__.py
yaci_client/api/account_api/get_address_amounts.py
yaci_client/api/account_api/get_address_balance.py
yaci_client/api/account_api/get_address_balance_at_time.py
yaci_client/api/account_api/get_stake_account_details.py
yaci_client/api/account_api/get_stake_address_balance.py
yaci_client/api/account_api/get_stake_address_balance_at_time.py
yaci_client/api/account_service/__init__.py
yaci_client/api/account_service/get_stake_de_registrations.py
yaci_client/api/account_service/get_stake_delegations.py
yaci_client/api/account_service/get_stake_registrations.py
yaci_client/api/account_service/get_withdrawals_by_account.py
yaci_client/api/address_service/__init__.py
yaci_client/api/address_service/get_utxos_1.py
yaci_client/api/address_service/get_utxos_for_asset.py
yaci_client/api/asset_api/__init__.py
yaci_client/api/asset_api/get_addresses_by_asset.py
yaci_client/api/asset_service/__init__.py
yaci_client/api/asset_service/get_asset_txs_by_fingerprint.py
yaci_client/api/asset_service/get_asset_txs_by_policy_id.py
yaci_client/api/asset_service/get_asset_txs_by_tx.py
yaci_client/api/asset_service/get_asset_txs_by_unit.py
yaci_client/api/asset_service/get_asset_utxos.py
yaci_client/api/asset_service/get_supply_by_fingerprint.py
yaci_client/api/asset_service/get_supply_by_policy.py
yaci_client/api/asset_service/get_supply_by_unit.py
yaci_client/api/block_service/__init__.py
yaci_client/api/block_service/get_block_by_number.py
yaci_client/api/block_service/get_blocks.py
yaci_client/api/block_service/get_blocks_by_slot_leader_epoch.py
yaci_client/api/block_service/get_latest_block.py
yaci_client/api/block_service/get_transactions_1.py
yaci_client/api/committee_service/__init__.py
yaci_client/api/committee_service/get_committee_de_registrations.py
yaci_client/api/committee_service/get_committee_registrations.py
yaci_client/api/d_rep_service/__init__.py
yaci_client-1.0.dist-info/METADATA
yaci_client-1.0.dist-info/WHEEL
yaci_client-1.0.dist-info/RECORD
