Metadata-Version: 2.1
Name: yaci_client
Version: 1.0
Summary: A client library for accessing Yaci Store API
Home-page: https://github.com/Kingpin-Apps/Yaci-client.git
License: MIT
Author: Hareem Adderley
Author-email: haddderley@kingpinapps.com
Requires-Python: >=3.8.1,<4.0.0
Classifier: License :: OSI Approved :: MIT License
Classifier: Programming Language :: Python :: 3
Classifier: Programming Language :: Python :: 3.9
Classifier: Programming Language :: Python :: 3.10
Classifier: Programming Language :: Python :: 3.11
Classifier: Programming Language :: Python :: 3.12
Requires-Dist: attrs (>=21.3.0)
Requires-Dist: httpx (>=0.20.0,<0.28.0)
Requires-Dist: python-dateutil (>=2.8.0,<3.0.0)
Project-URL: Repository, https://github.com/Kingpin-Apps/Yaci-client.git
